{"format":2,"version":"6.5.0","globals":"225f4943ba474fab38f122dc32445d06","files":{"d_923618c1a6891a60___init___py":{"hash":"3c77fc9ef7f887ac2508d4109cf92472","index":{"nums":[0,1,0,0,0,0,0,0],"html_filename":"d_923618c1a6891a60___init___py.html","relative_filename":"art/__init__.py"}},"d_923618c1a6891a60_admin_py":{"hash":"ab4aa3f59374b8e1caef4bb58ab522cb","index":{"nums":[0,1,49,0,5,0,0,0],"html_filename":"d_923618c1a6891a60_admin_py.html","relative_filename":"art/admin.py"}},"d_923618c1a6891a60_apps_py":{"hash":"5ed1bd454acfa81ba231167d786f9ef7","index":{"nums":[0,1,5,0,0,0,0,0],"html_filename":"d_923618c1a6891a60_apps_py.html","relative_filename":"art/apps.py"}},"d_923618c1a6891a60_forms_py":{"hash":"138ef505a0a65b7ef29293cb27bae9e7","index":{"nums":[0,1,3,0,0,0,0,0],"html_filename":"d_923618c1a6891a60_forms_py.html","relative_filename":"art/forms.py"}},"d_923618c1a6891a60_middlewares_py":{"hash":"6fc8311d82f235dba9aa8e8376ec4d8a","index":{"nums":[0,1,28,0,2,0,0,0],"html_filename":"d_923618c1a6891a60_middlewares_py.html","relative_filename":"art/middlewares.py"}},"d_04bed4a72609cf74_0001_initial_py":{"hash":"9ccc7af30fc80c488f11396d7c70e874","index":{"nums":[0,1,7,0,0,0,0,0],"html_filename":"d_04bed4a72609cf74_0001_initial_py.html","relative_filename":"art/migrations/0001_initial.py"}},"d_04bed4a72609cf74___init___py":{"hash":"3c77fc9ef7f887ac2508d4109cf92472","index":{"nums":[0,1,0,0,0,0,0,0],"html_filename":"d_04bed4a72609cf74___init___py.html","relative_filename":"art/migrations/__init__.py"}},"d_923618c1a6891a60_models_py":{"hash":"f43d76ae7576dc3f05a5ff8ba9a2c63e","index":{"nums":[0,1,105,0,9,0,0,0],"html_filename":"d_923618c1a6891a60_models_py.html","relative_filename":"art/models.py"}},"d_923618c1a6891a60_sitemaps_py":{"hash":"1863dba75730a5439bff1fc482af215b","index":{"nums":[0,1,31,0,0,0,0,0],"html_filename":"d_923618c1a6891a60_sitemaps_py.html","relative_filename":"art/sitemaps.py"}},"d_2f433b4f42cdffa2___init___py":{"hash":"3c77fc9ef7f887ac2508d4109cf92472","index":{"nums":[0,1,0,0,0,0,0,0],"html_filename":"d_2f433b4f42cdffa2___init___py.html","relative_filename":"art/templatetags/__init__.py"}},"d_2f433b4f42cdffa2_tmpl_extras_py":{"hash":"6daa641a2d36f91da170fe9bc3dee2be","index":{"nums":[0,1,16,0,0,0,0,0],"html_filename":"d_2f433b4f42cdffa2_tmpl_extras_py.html","relative_filename":"art/templatetags/tmpl_extras.py"}},"d_43ec67518a4e6bb5___init___py":{"hash":"3c77fc9ef7f887ac2508d4109cf92472","index":{"nums":[0,1,0,0,0,0,0,0],"html_filename":"d_43ec67518a4e6bb5___init___py.html","relative_filename":"art/tests_art/__init__.py"}},"d_43ec67518a4e6bb5_model_setup_py":{"hash":"6bbcfd5bd7987709bbd57b9dd320bf76","index":{"nums":[0,1,14,0,0,0,0,0],"html_filename":"d_43ec67518a4e6bb5_model_setup_py.html","relative_filename":"art/tests_art/model_setup.py"}},"d_43ec67518a4e6bb5_test_contact_py":{"hash":"4076e7833b0f27f7c3ee771bbcbbf521","index":{"nums":[0,1,11,0,0,0,0,0],"html_filename":"d_43ec67518a4e6bb5_test_contact_py.html","relative_filename":"art/tests_art/test_contact.py"}},"d_43ec67518a4e6bb5_test_index_py":{"hash":"ff72492c3a6d0d9adbecef3beb9431b6","index":{"nums":[0,1,3,0,0,0,0,0],"html_filename":"d_43ec67518a4e6bb5_test_index_py.html","relative_filename":"art/tests_art/test_index.py"}},"d_43ec67518a4e6bb5_test_model_plus_py":{"hash":"bdb195ca5307e9b423b2a98219460fd7","index":{"nums":[0,1,74,0,0,0,0,0],"html_filename":"d_43ec67518a4e6bb5_test_model_plus_py.html","relative_filename":"art/tests_art/test_model_plus.py"}},"d_43ec67518a4e6bb5_test_robots_py":{"hash":"6240a94b2c969f748a321896edac7e61","index":{"nums":[0,1,10,0,0,0,0,0],"html_filename":"d_43ec67518a4e6bb5_test_robots_py.html","relative_filename":"art/tests_art/test_robots.py"}},"d_43ec67518a4e6bb5_test_tags_py":{"hash":"beba07b92523e4b801568366d0e0e386","index":{"nums":[0,1,6,0,0,0,0,0],"html_filename":"d_43ec67518a4e6bb5_test_tags_py.html","relative_filename":"art/tests_art/test_tags.py"}},"d_43ec67518a4e6bb5_test_thanks_py":{"hash":"13d5c4cdc7c3815d9629a0566524f92d","index":{"nums":[0,1,11,0,0,0,0,0],"html_filename":"d_43ec67518a4e6bb5_test_thanks_py.html","relative_filename":"art/tests_art/test_thanks.py"}},"d_923618c1a6891a60_urls_py":{"hash":"15c51e2e2cb86dd973be34fe23397582","index":{"nums":[0,1,8,0,0,0,0,0],"html_filename":"d_923618c1a6891a60_urls_py.html","relative_filename":"art/urls.py"}},"d_86176946a80214f3___init___py":{"hash":"0b93772a6d4920b7b90cc33790ddd952","index":{"nums":[0,1,4,0,0,0,0,0],"html_filename":"d_86176946a80214f3___init___py.html","relative_filename":"art/views/__init__.py"}},"d_86176946a80214f3_contact_py":{"hash":"c99fe7754682a89ad68cd115c67d9fd2","index":{"nums":[0,1,45,0,17,0,0,0],"html_filename":"d_86176946a80214f3_contact_py.html","relative_filename":"art/views/contact.py"}},"d_86176946a80214f3_detail_py":{"hash":"fc867e638d063a8e879b3b43addbda8d","index":{"nums":[0,1,53,0,7,0,0,0],"html_filename":"d_86176946a80214f3_detail_py.html","relative_filename":"art/views/detail.py"}},"d_86176946a80214f3_index_py":{"hash":"10d0853d90903e7e1ff32e6523964e9c","index":{"nums":[0,1,23,0,0,0,0,0],"html_filename":"d_86176946a80214f3_index_py.html","relative_filename":"art/views/index.py"}},"d_86176946a80214f3_tasks_py":{"hash":"bd647bfe4f930c01c048a8c7b0387090","index":{"nums":[0,1,6,0,2,0,0,0],"html_filename":"d_86176946a80214f3_tasks_py.html","relative_filename":"art/views/tasks.py"}},"manage_py":{"hash":"5d63306b165321d4cd5411b775403b93","index":{"nums":[0,1,12,0,2,0,0,0],"html_filename":"manage_py.html","relative_filename":"manage.py"}},"d_1ff0e79755c87889___init___py":{"hash":"79e50815039d764122e7ab9a197539fa","index":{"nums":[0,1,2,0,0,0,0,0],"html_filename":"d_1ff0e79755c87889___init___py.html","relative_filename":"project/__init__.py"}},"d_1ff0e79755c87889_celery_py":{"hash":"d824aa9c774b1d3fbd9636a1f94ccd08","index":{"nums":[0,1,6,0,0,0,0,0],"html_filename":"d_1ff0e79755c87889_celery_py.html","relative_filename":"project/celery.py"}},"d_1ff0e79755c87889_settings_py":{"hash":"c06efe9bbaee0d315c9002e09645e4a1","index":{"nums":[0,1,63,0,3,0,0,0],"html_filename":"d_1ff0e79755c87889_settings_py.html","relative_filename":"project/settings.py"}},"d_1ff0e79755c87889_urls_py":{"hash":"b2f1ffc5aad44c6471167b8512a10838","index":{"nums":[0,1,13,0,3,0,0,0],"html_filename":"d_1ff0e79755c87889_urls_py.html","relative_filename":"project/urls.py"}},"d_0b432362bbcfff94___init___py":{"hash":"3c77fc9ef7f887ac2508d4109cf92472","index":{"nums":[0,1,0,0,0,0,0,0],"html_filename":"d_0b432362bbcfff94___init___py.html","relative_filename":"restapi/__init__.py"}},"d_0b432362bbcfff94_apps_py":{"hash":"6d2f0cfaf73324d649cc6f05813a1fac","index":{"nums":[0,1,4,0,0,0,0,0],"html_filename":"d_0b432362bbcfff94_apps_py.html","relative_filename":"restapi/apps.py"}},"d_027cfee987fdc010___init___py":{"hash":"81aba3fb7a97087522e45dc781440f94","index":{"nums":[0,1,3,0,0,0,0,0],"html_filename":"d_027cfee987fdc010___init___py.html","relative_filename":"restapi/base/__init__.py"}},"d_027cfee987fdc010_serializers_py":{"hash":"3b9d53c43dbad755e5d84bdd8c4ee69b","index":{"nums":[0,1,29,0,0,0,0,0],"html_filename":"d_027cfee987fdc010_serializers_py.html","relative_filename":"restapi/base/serializers.py"}},"d_027cfee987fdc010_views_py":{"hash":"55c9b87e3e0bd01c254b144ddcd3cc5d","index":{"nums":[0,1,30,0,0,0,0,0],"html_filename":"d_027cfee987fdc010_views_py.html","relative_filename":"restapi/base/views.py"}},"d_ce1560ab78118e4b___init___py":{"hash":"3c77fc9ef7f887ac2508d4109cf92472","index":{"nums":[0,1,0,0,0,0,0,0],"html_filename":"d_ce1560ab78118e4b___init___py.html","relative_filename":"restapi/tests_rest/__init__.py"}},"d_ce1560ab78118e4b_test_base_py":{"hash":"4dc79440f3d791e3b91f258ad759c80f","index":{"nums":[0,1,17,0,0,0,0,0],"html_filename":"d_ce1560ab78118e4b_test_base_py.html","relative_filename":"restapi/tests_rest/test_base.py"}},"d_ce1560ab78118e4b_test_users_py":{"hash":"826046358e07fa5f14897c6686220bc9","index":{"nums":[0,1,10,0,0,0,0,0],"html_filename":"d_ce1560ab78118e4b_test_users_py.html","relative_filename":"restapi/tests_rest/test_users.py"}},"d_0b432362bbcfff94_urls_py":{"hash":"856e8530e870f3759d9cdfb11faa4399","index":{"nums":[0,1,15,0,0,0,0,0],"html_filename":"d_0b432362bbcfff94_urls_py.html","relative_filename":"restapi/urls.py"}},"d_19fd87c290771d52___init___py":{"hash":"d2bd3143491e1f4b69ed4d6812289769","index":{"nums":[0,1,3,0,0,0,0,0],"html_filename":"d_19fd87c290771d52___init___py.html","relative_filename":"restapi/users/__init__.py"}},"d_19fd87c290771d52_serializers_py":{"hash":"21d0f12a2334360c3c7639c038b35bc0","index":{"nums":[0,1,47,0,20,0,0,0],"html_filename":"d_19fd87c290771d52_serializers_py.html","relative_filename":"restapi/users/serializers.py"}},"d_19fd87c290771d52_views_py":{"hash":"6233a621f6fb105850532accdf07caff","index":{"nums":[0,1,37,0,11,0,0,0],"html_filename":"d_19fd87c290771d52_views_py.html","relative_filename":"restapi/users/views.py"}},"d_0b432362bbcfff94_views_py":{"hash":"a99a2b9a745c1482c9ad8697518cffe0","index":{"nums":[0,1,7,0,0,0,0,0],"html_filename":"d_0b432362bbcfff94_views_py.html","relative_filename":"restapi/views.py"}},"d_f6c68bdc9becfc1e___init___py":{"hash":"3c77fc9ef7f887ac2508d4109cf92472","index":{"nums":[0,1,0,0,0,0,0,0],"html_filename":"d_f6c68bdc9becfc1e___init___py.html","relative_filename":"users/__init__.py"}},"d_f6c68bdc9becfc1e_admin_py":{"hash":"c24e8c95af7a8447b379ecea12ff6990","index":{"nums":[0,1,1,0,0,0,0,0],"html_filename":"d_f6c68bdc9becfc1e_admin_py.html","relative_filename":"users/admin.py"}},"d_f6c68bdc9becfc1e_apps_py":{"hash":"22b260c23215d213a6927b9875b05bef","index":{"nums":[0,1,5,0,0,0,0,0],"html_filename":"d_f6c68bdc9becfc1e_apps_py.html","relative_filename":"users/apps.py"}},"d_f6c68bdc9becfc1e_authentication_py":{"hash":"e567fc9005b08df9a73f795df3d6ba92","index":{"nums":[0,1,16,0,5,0,0,0],"html_filename":"d_f6c68bdc9becfc1e_authentication_py.html","relative_filename":"users/authentication.py"}},"d_f6c68bdc9becfc1e_forms_py":{"hash":"e6b5a24f52ec7be8a367ef6d94c80cb7","index":{"nums":[0,1,25,0,0,0,0,0],"html_filename":"d_f6c68bdc9becfc1e_forms_py.html","relative_filename":"users/forms.py"}},"d_f6c68bdc9becfc1e_models_py":{"hash":"e222c874356abbbfbc7c693ffecbbf13","index":{"nums":[0,1,1,0,0,0,0,0],"html_filename":"d_f6c68bdc9becfc1e_models_py.html","relative_filename":"users/models.py"}},"d_492465921dbdaa3e___init___py":{"hash":"3c77fc9ef7f887ac2508d4109cf92472","index":{"nums":[0,1,0,0,0,0,0,0],"html_filename":"d_492465921dbdaa3e___init___py.html","relative_filename":"users/tests_users/__init__.py"}},"d_492465921dbdaa3e_test_login_py":{"hash":"e787efd27279f4901c7b3ea97a481066","index":{"nums":[0,1,11,0,0,0,0,0],"html_filename":"d_492465921dbdaa3e_test_login_py.html","relative_filename":"users/tests_users/test_login.py"}},"d_492465921dbdaa3e_test_password_change_done_py":{"hash":"277687236a3ee27547cb173ade28b1ca","index":{"nums":[0,1,11,0,0,0,0,0],"html_filename":"d_492465921dbdaa3e_test_password_change_done_py.html","relative_filename":"users/tests_users/test_password_change_done.py"}},"d_492465921dbdaa3e_test_password_reset_py":{"hash":"0172e062510fb91a37b9c093a926a73a","index":{"nums":[0,1,11,0,0,0,0,0],"html_filename":"d_492465921dbdaa3e_test_password_reset_py.html","relative_filename":"users/tests_users/test_password_reset.py"}},"d_492465921dbdaa3e_test_password_reset_complete_py":{"hash":"dc1157cc7d6700036e81541bd05a7b79","index":{"nums":[0,1,11,0,0,0,0,0],"html_filename":"d_492465921dbdaa3e_test_password_reset_complete_py.html","relative_filename":"users/tests_users/test_password_reset_complete.py"}},"d_492465921dbdaa3e_test_password_reset_done_py":{"hash":"0dfd549002ca8b445756ee964b6ad529","index":{"nums":[0,1,11,0,0,0,0,0],"html_filename":"d_492465921dbdaa3e_test_password_reset_done_py.html","relative_filename":"users/tests_users/test_password_reset_done.py"}},"d_492465921dbdaa3e_test_signup_py":{"hash":"53de1c62fa3294a3ee8427b11f33adc8","index":{"nums":[0,1,11,0,0,0,0,0],"html_filename":"d_492465921dbdaa3e_test_signup_py.html","relative_filename":"users/tests_users/test_signup.py"}},"d_f6c68bdc9becfc1e_urls_py":{"hash":"a374d58b3dad39e238eb64db063361c8","index":{"nums":[0,1,5,0,0,0,0,0],"html_filename":"d_f6c68bdc9becfc1e_urls_py.html","relative_filename":"users/urls.py"}},"d_f6c68bdc9becfc1e_views_py":{"hash":"40a20d0a2a0a88169835204d75c8af9f","index":{"nums":[0,1,24,0,0,0,0,0],"html_filename":"d_f6c68bdc9becfc1e_views_py.html","relative_filename":"users/views.py"}},"d_752d35e2d1a1d542___init___py":{"hash":"3c77fc9ef7f887ac2508d4109cf92472","index":{"nums":[0,1,0,0,0,0,0,0],"html_filename":"d_752d35e2d1a1d542___init___py.html","relative_filename":"restapi/tests_restapi/__init__.py"}},"d_752d35e2d1a1d542_test_base_py":{"hash":"2fccf0cd74f5e6961d7a29a32178777b","index":{"nums":[0,1,17,0,0,0,0,0],"html_filename":"d_752d35e2d1a1d542_test_base_py.html","relative_filename":"restapi/tests_restapi/test_base.py"}},"d_752d35e2d1a1d542_test_users_py":{"hash":"9cc8c8b9600c7739202ea7d6cd4522d3","index":{"nums":[0,1,10,0,0,0,0,0],"html_filename":"d_752d35e2d1a1d542_test_users_py.html","relative_filename":"restapi/tests_restapi/test_users.py"}}}}